wot_pdf/__init__.py
wot_pdf/cli.py
wot_pdf/content_analyzer.py
wot_pdf/content_preprocessor.py
wot_pdf/engine_selector.py
wot_pdf/abstractions/__init__.py
wot_pdf/abstractions/base/__init__.py
wot_pdf/abstractions/base/engine.py
wot_pdf/abstractions/base/processor.py
wot_pdf/abstractions/base/service.py
wot_pdf/abstractions/interfaces/__init__.py
wot_pdf/abstractions/protocols/__init__.py
wot_pdf/abstractions/protocols/engine.py
wot_pdf/adapters/__init__.py
wot_pdf/adapters/enhanced_typst_adapter.py
wot_pdf/adapters/simplified_reportlab_adapter.py
wot_pdf/adapters/simplified_typst_adapter.py
wot_pdf/api/__init__.py
wot_pdf/api/main_api.py
wot_pdf/builders/diagram_processor.py
wot_pdf/builders/markdown_processor.py
wot_pdf/builders/production_builder.py
wot_pdf/builders/production_builder_new.py
wot_pdf/builders/production_engine.py
wot_pdf/config/__init__.py
wot_pdf/core/__init__.py
wot_pdf/core/base_engine.py
wot_pdf/core/book_generator.py
wot_pdf/core/content_analyzer.py
wot_pdf/core/content_preprocessor.py
wot_pdf/core/engine_configuration_protocol.py
wot_pdf/core/engine_selector.py
wot_pdf/core/future_proofing_system.py
wot_pdf/core/generator.py
wot_pdf/core/intelligent_engine_router.py
wot_pdf/core/intelligent_engine_router_new.py
wot_pdf/core/template_manager.py
wot_pdf/core/test_modular_architecture.py
wot_pdf/core/typst_content_optimizer.py
wot_pdf/core/typst_mermaid_handler.py
wot_pdf/core/unified_content_processor_factory.py
wot_pdf/core/unified_typst_content_optimizer.py
wot_pdf/core/unified_typst_content_optimizer_v2.py
wot_pdf/core/typst_optimizers/__init__.py
wot_pdf/core/typst_optimizers/advanced_engine.py
wot_pdf/core/typst_optimizers/character_handlers.py
wot_pdf/core/typst_optimizers/code_block_processors.py
wot_pdf/core/typst_optimizers/content_converters.py
wot_pdf/core/typst_optimizers/core_optimizer.py
wot_pdf/core/typst_optimizers/legacy_processors.py
wot_pdf/core/unified_optimizers/__init__.py
wot_pdf-1.2.7.dist-info/licenses/LICENSE
wot_pdf-1.2.7.dist-info/METADATA
wot_pdf-1.2.7.dist-info/WHEEL
wot_pdf-1.2.7.dist-info/entry_points.txt
wot_pdf-1.2.7.dist-info/top_level.txt
wot_pdf-1.2.7.dist-info/RECORD
