Metadata-Version: 2.4
Name: wot-pdf
Version: 1.2.7
Summary: WOT-PDF v1.2.7: Comprehensive PDF Generation with Version Consistency
Author-email: Work Organizing Tools <info@wot-tools.com>
License-Expression: MIT
Project-URL: Homepage, https://bitbucket.org/tinezivic/wot-pdf
Project-URL: Documentation, https://wot-pdf.readthedocs.io/
Project-URL: Repository, https://bitbucket.org/tinezivic/wot-pdf.git
Project-URL: Issues, https://bitbucket.org/tinezivic/wot-pdf/issues
Keywords: pdf,typst,reportlab,markdown,mermaid,diagrams,book,generation,professional,automation
Classifier: Development Status :: 5 - Production/Stable
Classifier: Intended Audience :: Developers
Classifier: Programming Language :: Python :: 3
Classifier: Programming Language :: Python :: 3.8
Classifier: Programming Language :: Python :: 3.9
Classifier: Programming Language :: Python :: 3.10
Classifier: Programming Language :: Python :: 3.11
Classifier: Programming Language :: Python :: 3.12
Classifier: Operating System :: OS Independent
Classifier: Topic :: Text Processing :: Markup
Classifier: Topic :: Office/Business :: Office Suites
Classifier: Topic :: Software Development :: Libraries :: Python Modules
Requires-Python: >=3.8
License-File: LICENSE
Requires-Dist: reportlab>=4.0.0
Requires-Dist: Pillow>=10.0.0
Requires-Dist: markdown>=3.4.0
Requires-Dist: pathlib-mate>=1.0.0
Requires-Dist: requests>=2.28.0
Provides-Extra: dev
Requires-Dist: pytest>=7.0.0; extra == "dev"
Requires-Dist: pytest-cov>=4.0.0; extra == "dev"
Requires-Dist: black>=23.0.0; extra == "dev"
Requires-Dist: flake8>=6.0.0; extra == "dev"
Requires-Dist: mypy>=1.0.0; extra == "dev"
Requires-Dist: twine>=4.0.0; extra == "dev"
Requires-Dist: build>=0.10.0; extra == "dev"
Dynamic: license-file
